{
	"textures": {
		"0": "tamagottimod:block/soko",
		"1": "tamagottimod:block/sshield0"
	},
	"elements": [
		{
			"from": [5, 1, 8],
			"to": [10, 8, 8.575],
			"faces": {
				"north": {"uv": [6, 9, 11, 16], "texture": "#1"},
				"east": {"uv": [0, 0, 0.4, 7], "texture": "#1"},
				"south": {"uv": [0, 0, 5, 7], "texture": "#0"},
				"west": {"uv": [0, 0, 0.4, 7], "texture": "#1"},
				"up": {"uv": [0, 15.7, 5, 16], "texture": "#1"},
				"down": {"uv": [6, 15.6, 11, 16], "rotation": 180, "texture": "#1"}
			}
		},
		{
			"from": [9, 8, 8],
			"to": [12, 11, 8.575],
			"faces": {
				"north": {"uv": [0, 0, 3, 3], "texture": "#1"},
				"east": {"uv": [0, 0, 0.4, 3], "texture": "#1"},
				"south": {"uv": [0, 0, 3, 3], "texture": "#0"},
				"west": {"uv": [0, 0, 0.4, 3], "texture": "#1"},
				"up": {"uv": [0, 0, 3, 0.4], "rotation": 180, "texture": "#1"},
				"down": {"uv": [0, 0, 3, 0.4], "rotation": 180, "texture": "#1"}
			}
		},
		{
			"from": [3, 8, 8],
			"to": [6, 11, 8.575],
			"faces": {
				"north": {"uv": [13, 0, 16, 3], "texture": "#1"},
				"east": {"uv": [0, 0, 0.4, 3], "texture": "#1"},
				"south": {"uv": [0, 0, 3, 3], "texture": "#0"},
				"west": {"uv": [0, 0, 0.4, 3], "texture": "#1"},
				"up": {"uv": [13, 0, 16, 0.4], "rotation": 180, "texture": "#1"},
				"down": {"uv": [0, 0, 3, 0.4], "texture": "#1"}
			}
		},
		{
			"from": [6, 8, 8],
			"to": [9, 10, 8.3],
			"faces": {
				"north": {"uv": [6, 0, 9, 2], "texture": "#1"},
				"east": {"uv": [0, 0, 0.3, 2], "texture": "#missing"},
				"south": {"uv": [0, 0, 3, 2], "texture": "#0"},
				"west": {"uv": [0, 0, 0.3, 2], "texture": "#missing"},
				"up": {"uv": [6, 0, 9, 0.3], "rotation": 180, "texture": "#1"},
				"down": {"uv": [0, 0, 3, 0.3], "texture": "#missing"}
			}
		},
		{
			"from": [10, 3, 8],
			"to": [11.5, 8, 8.3],
			"faces": {
				"north": {"uv": [0, 11, 1.5, 16], "texture": "#1"},
				"east": {"uv": [0, 11, 0.3, 16], "texture": "#1"},
				"south": {"uv": [0, 0, 1.5, 5], "texture": "#0"},
				"west": {"uv": [0, 0, 0.3, 5], "texture": "#missing"},
				"up": {"uv": [0, 0, 1.5, 0.3], "texture": "#missing"},
				"down": {"uv": [0, 15.7, 1.5, 16], "rotation": 180, "texture": "#1"}
			}
		},
		{
			"from": [3.5, 3, 8],
			"to": [5, 8, 8.3],
			"faces": {
				"north": {"uv": [14.5, 11, 16, 16], "texture": "#1"},
				"east": {"uv": [0, 0, 0.3, 5], "texture": "#missing"},
				"south": {"uv": [0, 0, 1.5, 5], "texture": "#0"},
				"west": {"uv": [0, 0, 0.3, 5], "texture": "#1"},
				"up": {"uv": [0, 0, 1.5, 0.3], "texture": "#missing"},
				"down": {"uv": [0, 0, 1.5, 0.3], "texture": "#1"}
			}
		}
	],
	"display": {
		"thirdperson_righthand": {
			"rotation": [67, 0, 0],
			"translation": [0, 1.5, 1.75]
		},
		"thirdperson_lefthand": {
			"rotation": [62, 0, 0],
			"translation": [0, 1.5, 1.75]
		},
		"firstperson_righthand": {
			"translation": [0, 4.5, 0],
			"scale": [1.5, 1.5, 1.5]
		},
		"firstperson_lefthand": {
			"translation": [0, 4.5, 0],
			"scale": [1.5, 1.5, 1.5]
		},
		"ground": {
			"translation": [0, 0.5, 0],
			"scale": [0.75, 0.75, 0.75]
		},
		"gui": {
			"rotation": [0, -180, 0],
			"translation": [-0.5, 2.75, 0],
			"scale": [1.5, 1.5, 1]
		},
		"fixed": {
			"translation": [0, 3.25, -2],
			"scale": [1.75, 1.75, 1.75]
		}
	}
}